file_validator/__init__.py
file_validator/checker.py
file_validator/config.py
file_validator/exception.py
file_validator/extension.py
file_validator/main.py
universal_file_validator-0.0.1.dist-info/licenses/LICENSE
universal_file_validator-0.0.1.dist-info/METADATA
universal_file_validator-0.0.1.dist-info/WHEEL
universal_file_validator-0.0.1.dist-info/top_level.txt
universal_file_validator-0.0.1.dist-info/RECORD
