Metadata-Version: 2.4
Name: universal-file-validator
Version: 0.0.1
Summary: Библиотека для валидации файлов
Author-email: Денис Шахбазян <otbephncb@gmail.com>
Project-URL: Homepage, https://github.com/DenisShahbazyan/File_Validator
Project-URL: Bug Tracker, https://github.com/DenisShahbazyan/File_Validator/issues
Classifier: Development Status :: 4 - Beta
Classifier: Programming Language :: Python :: 3.10
Classifier: Programming Language :: Python :: 3.11
Classifier: Programming Language :: Python :: 3.12
Classifier: License :: OSI Approved :: MIT License
Requires-Python: >=3.10
License-File: LICENSE
Requires-Dist: python-magic==0.4.27
Dynamic: license-file
